{
  "code_repository": [
    {
      "confidence": 1,
      "result": {
        "type": "Url",
        "value": "https://github.com/howon-kim/Urban-Data-Analytics"
      },
      "technique": "GitHub_API"
    }
  ],
  "date_created": [
    {
      "confidence": 1,
      "result": {
        "type": "Date",
        "value": "2020-06-02T05:27:26Z"
      },
      "technique": "GitHub_API"
    }
  ],
  "date_updated": [
    {
      "confidence": 1,
      "result": {
        "type": "Date",
        "value": "2022-02-24T12:46:02Z"
      },
      "technique": "GitHub_API"
    }
  ],
  "description": [
    {
      "confidence": 1,
      "result": {
        "type": "String",
        "value": "Systematic approaches to collecting, analyzing, modeling, and interpreting data to inform research, and, ultimately, urban planning practice and policymaking."
      },
      "technique": "GitHub_API"
    },
    {
      "confidence": 1,
      "result": {
        "original_header": "Description",
        "parent_header": [
          "Covid-19\u2019s Effects on Bike Sharing in San Francisco"
        ],
        "type": "Text_excerpt",
        "value": "educational environment, it has two community colleges, seven primary schools, two junior high\nschools, and a high school. In terms of the economic environment, Union City has three large health\ncare providers and a 100-acre shopping center, which has provided many local employment\nopportunities. In terms of population composition, the largest ethnic group in Union City is Asians,\nfollowed by Hispanics and whites, while blacks only account for 5 percent. More specific data is expanded\nbelow. The community profile is Tract 4403.8 and it is the main research area of the portfolio. It is located in\nthe city center of Union City, covering an area of 0.71 square miles. The specific data will also be developed\nlater. (In this portfolio, the words area/location is referred to as Tract 4403.8.)\n"
      },
      "source": "https://raw.githubusercontent.com/howon-kim/Urban-Data-Analytics/master/README.md",
      "technique": "header_analysis"
    },
    {
      "confidence": 0.8682880191361709,
      "result": {
        "original_header": "Bay Area Data Analytics",
        "type": "Text_excerpt",
        "value": "Department of City and Regional Planning at UC Berkeley\n \n"
      },
      "source": "https://raw.githubusercontent.com/howon-kim/Urban-Data-Analytics/master/README.md",
      "technique": "supervised_classification"
    },
    {
      "confidence": 0.9979851560760834,
      "result": {
        "original_header": "Variables and Finding",
        "type": "Text_excerpt",
        "value": "Dynamics) data from 2010 and 2018. The data we are focusing on this portfolio is the population/household\nstructure, racial/ethnic composition, income and poverty levels, and labor force characteristics. Our main goal\nis to explore the impact of income changes on different ethnic groups.\n \n"
      },
      "source": "https://raw.githubusercontent.com/howon-kim/Urban-Data-Analytics/master/README.md",
      "technique": "supervised_classification"
    }
  ],
  "download_url": [
    {
      "confidence": 1,
      "result": {
        "type": "Url",
        "value": "https://github.com/howon-kim/Urban-Data-Analytics/releases"
      },
      "technique": "GitHub_API"
    }
  ],
  "executable_example": [
    {
      "confidence": 1,
      "result": {
        "format": "jupyter_notebook",
        "type": "Url",
        "value": "https://raw.githubusercontent.com/howon-kim/Urban-Data-Analytics/master/SF_Bikeshare_Data/Analyze.ipynb"
      },
      "source": "https://raw.githubusercontent.com/howon-kim/Urban-Data-Analytics/master/SF_Bikeshare_Data/Analyze.ipynb",
      "technique": "file_exploration"
    }
  ],
  "forks_count": [
    {
      "confidence": 1,
      "result": {
        "type": "Number",
        "value": 0
      },
      "technique": "GitHub_API"
    }
  ],
  "forks_url": [
    {
      "confidence": 1,
      "result": {
        "type": "Url",
        "value": "https://api.github.com/repos/howon-kim/Urban-Data-Analytics/forks"
      },
      "technique": "GitHub_API"
    }
  ],
  "full_name": [
    {
      "confidence": 1,
      "result": {
        "type": "String",
        "value": "howon-kim/Urban-Data-Analytics"
      },
      "technique": "GitHub_API"
    }
  ],
  "full_title": [
    {
      "confidence": 1,
      "result": {
        "type": "String",
        "value": "Bay Area Data Analytics"
      },
      "source": "https://raw.githubusercontent.com/howon-kim/Urban-Data-Analytics/master/README.md",
      "technique": "regular_expression"
    }
  ],
  "issue_tracker": [
    {
      "confidence": 1,
      "result": {
        "type": "Url",
        "value": "https://api.github.com/repos/howon-kim/Urban-Data-Analytics/issues"
      },
      "technique": "GitHub_API"
    }
  ],
  "keywords": [
    {
      "confidence": 1,
      "result": {
        "type": "String",
        "value": "data-analysis, urban-analytics, urban-data-science"
      },
      "technique": "GitHub_API"
    }
  ],
  "name": [
    {
      "confidence": 1,
      "result": {
        "type": "String",
        "value": "Urban-Data-Analytics"
      },
      "technique": "GitHub_API"
    }
  ],
  "owner": [
    {
      "confidence": 1,
      "result": {
        "type": "User",
        "value": "howon-kim"
      },
      "technique": "GitHub_API"
    }
  ],
  "programming_languages": [
    {
      "confidence": 1,
      "result": {
        "name": "Jupyter Notebook",
        "size": 3459561,
        "type": "Programming_language",
        "value": "Jupyter Notebook"
      },
      "technique": "GitHub_API"
    },
    {
      "confidence": 1,
      "result": {
        "name": "Rich Text Format",
        "size": 447,
        "type": "Programming_language",
        "value": "Rich Text Format"
      },
      "technique": "GitHub_API"
    }
  ],
  "readme_url": [
    {
      "confidence": 1,
      "result": {
        "type": "Url",
        "value": "https://raw.githubusercontent.com/howon-kim/Urban-Data-Analytics/master/README.md"
      },
      "technique": "file_exploration"
    }
  ],
  "somef_missing_categories": [
    "installation",
    "citation",
    "acknowledgement",
    "run",
    "download",
    "requirements",
    "contact",
    "contributors",
    "documentation",
    "license",
    "usage",
    "faq",
    "support",
    "identifier",
    "has_build_file"
  ],
  "somef_provenance": {
    "date": "2024-10-04 00:35:43",
    "somef_schema_version": "1.0.0",
    "somef_version": "0.9.5"
  },
  "stargazers_count": [
    {
      "confidence": 1,
      "result": {
        "type": "Number",
        "value": 1
      },
      "technique": "GitHub_API"
    }
  ]
}