{
  "code_repository": [
    {
      "confidence": 1,
      "result": {
        "type": "Url",
        "value": "https://github.com/MLMIP/LDNFSGB"
      },
      "technique": "GitHub_API"
    }
  ],
  "date_created": [
    {
      "confidence": 1,
      "result": {
        "type": "Date",
        "value": "2020-07-25T06:45:41Z"
      },
      "technique": "GitHub_API"
    }
  ],
  "date_updated": [
    {
      "confidence": 1,
      "result": {
        "type": "Date",
        "value": "2020-09-15T04:27:55Z"
      },
      "technique": "GitHub_API"
    }
  ],
  "description": [
    {
      "confidence": 0.9819353976355591,
      "result": {
        "original_header": "LDNFSGB:Predicting lncRNA-disease associations using network feature similarity and gradient boosting",
        "type": "Text_excerpt",
        "value": "\r\nFirst, we construct a feature vector to extract similarity information of different lncRNAs and diseases. Then,  an autoencoder is used to reduce the dimensionality of the feature vector. Finally, the gradientboosting classifier is used to predict lncRNA-disease associations.\r\n\r \n"
      },
      "source": "https://raw.githubusercontent.com/MLMIP/LDNFSGB/master/README.md",
      "technique": "supervised_classification"
    },
    {
      "confidence": 0.9934889257594682,
      "result": {
        "original_header": "Autoencoder.py",
        "type": "Text_excerpt",
        "value": "This part is mainly to reduce the dimensionality of the sample features.\r\n\r \n"
      },
      "source": "https://raw.githubusercontent.com/MLMIP/LDNFSGB/master/README.md",
      "technique": "supervised_classification"
    },
    {
      "confidence": 0.9850150784992489,
      "result": {
        "original_header": "Gradientboosting.py",
        "type": "Text_excerpt",
        "value": "It is mainly used for prediction of lncRNA-disease association.  At the same time, this part provides the performance evaluation of the model under 10-fold CV including AUC, accuracy, sensitive, precision, specificity and ROC curve drawing.\r\n\r\n\r\nThe original datasets used in this study are available from the corresponding references.\r\n\r\n\r\nReferences\r\nZhang, Y., Ye, F., Xiong, D. et al. LDNFSGB: prediction of long non-coding rna and disease association using network feature similarity and gradient boosting. BMC Bioinformatics 21, 377 (2020). https://doi.org/10.1186/s12859-020-03721-0\r\n \n"
      },
      "source": "https://raw.githubusercontent.com/MLMIP/LDNFSGB/master/README.md",
      "technique": "supervised_classification"
    }
  ],
  "download_url": [
    {
      "confidence": 1,
      "result": {
        "type": "Url",
        "value": "https://github.com/MLMIP/LDNFSGB/releases"
      },
      "technique": "GitHub_API"
    }
  ],
  "forks_count": [
    {
      "confidence": 1,
      "result": {
        "type": "Number",
        "value": 0
      },
      "technique": "GitHub_API"
    }
  ],
  "forks_url": [
    {
      "confidence": 1,
      "result": {
        "type": "Url",
        "value": "https://api.github.com/repos/MLMIP/LDNFSGB/forks"
      },
      "technique": "GitHub_API"
    }
  ],
  "full_name": [
    {
      "confidence": 1,
      "result": {
        "type": "String",
        "value": "MLMIP/LDNFSGB"
      },
      "technique": "GitHub_API"
    }
  ],
  "full_title": [
    {
      "confidence": 1,
      "result": {
        "type": "String",
        "value": "LDNFSGB:Predicting lncRNA-disease associations using network feature similarity and gradient boosting"
      },
      "source": "https://raw.githubusercontent.com/MLMIP/LDNFSGB/master/README.md",
      "technique": "regular_expression"
    }
  ],
  "issue_tracker": [
    {
      "confidence": 1,
      "result": {
        "type": "Url",
        "value": "https://api.github.com/repos/MLMIP/LDNFSGB/issues"
      },
      "technique": "GitHub_API"
    }
  ],
  "keywords": [
    {
      "confidence": 1,
      "result": {
        "type": "String",
        "value": ""
      },
      "technique": "GitHub_API"
    }
  ],
  "name": [
    {
      "confidence": 1,
      "result": {
        "type": "String",
        "value": "LDNFSGB"
      },
      "technique": "GitHub_API"
    }
  ],
  "owner": [
    {
      "confidence": 1,
      "result": {
        "type": "User",
        "value": "MLMIP"
      },
      "technique": "GitHub_API"
    }
  ],
  "programming_languages": [
    {
      "confidence": 1,
      "result": {
        "name": "Python",
        "size": 17119,
        "type": "Programming_language",
        "value": "Python"
      },
      "technique": "GitHub_API"
    }
  ],
  "readme_url": [
    {
      "confidence": 1,
      "result": {
        "type": "Url",
        "value": "https://raw.githubusercontent.com/MLMIP/LDNFSGB/master/README.md"
      },
      "technique": "file_exploration"
    }
  ],
  "somef_missing_categories": [
    "installation",
    "citation",
    "acknowledgement",
    "run",
    "download",
    "requirements",
    "contact",
    "contributors",
    "documentation",
    "license",
    "usage",
    "faq",
    "support",
    "identifier",
    "has_build_file",
    "executable_example"
  ],
  "somef_provenance": {
    "date": "2024-10-06 13:58:48",
    "somef_schema_version": "1.0.0",
    "somef_version": "0.9.5"
  },
  "stargazers_count": [
    {
      "confidence": 1,
      "result": {
        "type": "Number",
        "value": 2
      },
      "technique": "GitHub_API"
    }
  ]
}