{
  "application_domain": [
    {
      "confidence": 0.8247429471093192,
      "result": {
        "type": "String",
        "value": "Semantic web"
      },
      "technique": "supervised_classification"
    }
  ],
  "code_repository": [
    {
      "confidence": 1,
      "result": {
        "type": "Url",
        "value": "https://github.com/compsy/ACTman"
      },
      "technique": "GitHub_API"
    }
  ],
  "date_created": [
    {
      "confidence": 1,
      "result": {
        "type": "Date",
        "value": "2017-03-02T14:49:47Z"
      },
      "technique": "GitHub_API"
    }
  ],
  "date_updated": [
    {
      "confidence": 1,
      "result": {
        "type": "Date",
        "value": "2024-10-04T00:00:15Z"
      },
      "technique": "GitHub_API"
    }
  ],
  "description": [
    {
      "confidence": 1,
      "result": {
        "type": "String",
        "value": "Actigraphy manager"
      },
      "technique": "GitHub_API"
    },
    {
      "confidence": 0.9527452121173212,
      "result": {
        "original_header": "ACTman",
        "type": "Text_excerpt",
        "value": "ACTman manages Actigraphy data. \n"
      },
      "source": "https://raw.githubusercontent.com/compsy/ACTman/master/README.md",
      "technique": "supervised_classification"
    }
  ],
  "documentation": [
    {
      "confidence": 1,
      "result": {
        "type": "Url",
        "value": "https://github.com/compsy/ACTman/tree/master/inst/docs"
      },
      "technique": "file_exploration"
    }
  ],
  "download_url": [
    {
      "confidence": 1,
      "result": {
        "type": "Url",
        "value": "https://github.com/compsy/ACTman/releases"
      },
      "technique": "GitHub_API"
    }
  ],
  "forks_count": [
    {
      "confidence": 1,
      "result": {
        "type": "Number",
        "value": 1
      },
      "technique": "GitHub_API"
    }
  ],
  "forks_url": [
    {
      "confidence": 1,
      "result": {
        "type": "Url",
        "value": "https://api.github.com/repos/compsy/ACTman/forks"
      },
      "technique": "GitHub_API"
    }
  ],
  "full_name": [
    {
      "confidence": 1,
      "result": {
        "type": "String",
        "value": "compsy/ACTman"
      },
      "technique": "GitHub_API"
    }
  ],
  "full_title": [
    {
      "confidence": 1,
      "result": {
        "type": "String",
        "value": "ACTman"
      },
      "source": "https://raw.githubusercontent.com/compsy/ACTman/master/README.md",
      "technique": "regular_expression"
    }
  ],
  "has_build_file": [
    {
      "confidence": 1,
      "result": {
        "format": "dockerfile",
        "type": "Url",
        "value": "https://raw.githubusercontent.com/compsy/ACTman/master/Dockerfile"
      },
      "source": "https://raw.githubusercontent.com/compsy/ACTman/master/Dockerfile",
      "technique": "file_exploration"
    }
  ],
  "has_script_file": [
    {
      "confidence": 1,
      "result": {
        "type": "Url",
        "value": "https://raw.githubusercontent.com/compsy/ACTman/master/inst/bash/install-package-dependencies.sh"
      },
      "technique": "file_exploration"
    },
    {
      "confidence": 1,
      "result": {
        "type": "Url",
        "value": "https://raw.githubusercontent.com/compsy/ACTman/master/inst/bash/check_code_conventions.sh"
      },
      "technique": "file_exploration"
    },
    {
      "confidence": 1,
      "result": {
        "type": "Url",
        "value": "https://raw.githubusercontent.com/compsy/ACTman/master/inst/bash/test.sh"
      },
      "technique": "file_exploration"
    }
  ],
  "installation": [
    {
      "confidence": 0.9984985826529218,
      "result": {
        "original_header": "ACTman",
        "type": "Text_excerpt",
        "value": "To install, type the following: \n    install.packages('devtools')\n    devtools::install_github('compsy/ACTman') \n"
      },
      "source": "https://raw.githubusercontent.com/compsy/ACTman/master/README.md",
      "technique": "supervised_classification"
    }
  ],
  "issue_tracker": [
    {
      "confidence": 1,
      "result": {
        "type": "Url",
        "value": "https://api.github.com/repos/compsy/ACTman/issues"
      },
      "technique": "GitHub_API"
    }
  ],
  "keywords": [
    {
      "confidence": 1,
      "result": {
        "type": "String",
        "value": ""
      },
      "technique": "GitHub_API"
    }
  ],
  "license": [
    {
      "confidence": 1,
      "result": {
        "name": "Other",
        "spdx_id": "NOASSERTION",
        "type": "License",
        "url": null,
        "value": null
      },
      "technique": "GitHub_API"
    },
    {
      "confidence": 1,
      "result": {
        "type": "File_dump",
        "value": "YEAR: 2017\nCOPYRIGHT HOLDER: Yoram Kunkels\n"
      },
      "source": "https://raw.githubusercontent.com/compsy/ACTman/master/LICENSE",
      "technique": "file_exploration"
    }
  ],
  "logo": [
    {
      "confidence": 1,
      "result": {
        "type": "Url",
        "value": "https://circleci.com/gh/compsy/ACTman.svg?style=svg&amp;circle-token=d4a53fd8f5a7813e4cacd9265bb5de8fe8b44336"
      },
      "source": "https://raw.githubusercontent.com/compsy/ACTman/master/README.md",
      "technique": "regular_expression"
    }
  ],
  "name": [
    {
      "confidence": 1,
      "result": {
        "type": "String",
        "value": "ACTman"
      },
      "technique": "GitHub_API"
    }
  ],
  "owner": [
    {
      "confidence": 1,
      "result": {
        "type": "Organization",
        "value": "compsy"
      },
      "technique": "GitHub_API"
    }
  ],
  "programming_languages": [
    {
      "confidence": 1,
      "result": {
        "name": "R",
        "size": 98870,
        "type": "Programming_language",
        "value": "R"
      },
      "technique": "GitHub_API"
    },
    {
      "confidence": 1,
      "result": {
        "name": "CSS",
        "size": 7153,
        "type": "Programming_language",
        "value": "CSS"
      },
      "technique": "GitHub_API"
    },
    {
      "confidence": 1,
      "result": {
        "name": "JavaScript",
        "size": 4494,
        "type": "Programming_language",
        "value": "JavaScript"
      },
      "technique": "GitHub_API"
    },
    {
      "confidence": 1,
      "result": {
        "name": "Dockerfile",
        "size": 1143,
        "type": "Programming_language",
        "value": "Dockerfile"
      },
      "technique": "GitHub_API"
    },
    {
      "confidence": 1,
      "result": {
        "name": "Shell",
        "size": 666,
        "type": "Programming_language",
        "value": "Shell"
      },
      "technique": "GitHub_API"
    }
  ],
  "readme_url": [
    {
      "confidence": 1,
      "result": {
        "type": "Url",
        "value": "https://raw.githubusercontent.com/compsy/ACTman/master/README.md"
      },
      "technique": "file_exploration"
    }
  ],
  "somef_missing_categories": [
    "citation",
    "acknowledgement",
    "run",
    "download",
    "requirements",
    "contact",
    "contributors",
    "faq",
    "support",
    "identifier",
    "executable_example"
  ],
  "somef_provenance": {
    "date": "2024-10-06 17:31:46",
    "somef_schema_version": "1.0.0",
    "somef_version": "0.9.5"
  },
  "stargazers_count": [
    {
      "confidence": 1,
      "result": {
        "type": "Number",
        "value": 2
      },
      "technique": "GitHub_API"
    }
  ],
  "usage": [
    {
      "confidence": 1,
      "result": {
        "original_header": "Example use",
        "parent_header": [
          "ACTman"
        ],
        "type": "Text_excerpt",
        "value": "To get the actdata overview:\n\n    View(ACTman::ACTman(workdir = \"C:/Bibliotheek/Studie/PhD/Publishing/ACTman/R-part/mydata2\",\n                        myACTdevice = \"Actiwatch2\",\n                        iwantsleepanalysis = FALSE,\n                        plotactogram = FALSE,\n                        selectperiod = FALSE,\n                        startperiod = \"2016-10-03 00:00:00\",\n                        daysperiod = 14,\n                        tune = FALSE))\n\nType ?ACTman::ACTman for help.\n"
      },
      "source": "https://raw.githubusercontent.com/compsy/ACTman/master/README.md",
      "technique": "header_analysis"
    }
  ]
}