{
  "application_domain": [
    {
      "confidence": 29.68,
      "result": {
        "type": "String",
        "value": "Computer Vision"
      },
      "technique": "supervised_classification"
    }
  ],
  "code_repository": [
    {
      "confidence": 1,
      "result": {
        "type": "Url",
        "value": "https://github.com/w3user/SegDGAN"
      },
      "technique": "GitHub_API"
    }
  ],
  "date_created": [
    {
      "confidence": 1,
      "result": {
        "type": "Date",
        "value": "2020-09-10T03:39:17Z"
      },
      "technique": "GitHub_API"
    }
  ],
  "date_updated": [
    {
      "confidence": 1,
      "result": {
        "type": "Date",
        "value": "2020-09-10T04:40:12Z"
      },
      "technique": "GitHub_API"
    }
  ],
  "download_url": [
    {
      "confidence": 1,
      "result": {
        "type": "Url",
        "value": "https://github.com/w3user/SegDGAN/releases"
      },
      "technique": "GitHub_API"
    }
  ],
  "forks_count": [
    {
      "confidence": 1,
      "result": {
        "type": "Number",
        "value": 0
      },
      "technique": "GitHub_API"
    }
  ],
  "forks_url": [
    {
      "confidence": 1,
      "result": {
        "type": "Url",
        "value": "https://api.github.com/repos/w3user/SegDGAN/forks"
      },
      "technique": "GitHub_API"
    }
  ],
  "full_name": [
    {
      "confidence": 1,
      "result": {
        "type": "String",
        "value": "w3user/SegDGAN"
      },
      "technique": "GitHub_API"
    }
  ],
  "full_title": [
    {
      "confidence": 1,
      "result": {
        "type": "String",
        "value": ""
      },
      "source": "https://raw.githubusercontent.com/w3user/SegDGAN/master/Readme.md",
      "technique": "regular_expression"
    }
  ],
  "installation": [
    {
      "confidence": 0.9956447554933429,
      "result": {
        "type": "Text_excerpt",
        "value": "This repository is the official repository of the article \"Automatic Segmentation of Prostate Magnetic Resonance Imaging\r\nUsing Generative Adversarial Networks\"\r\nTo train a model use the train.py file, you can use the following commands line to get the important arguments\r\n\r\n```shell\r\npython train.py -h\r\n```   \r\nYou can config the detailed parameters in the config.py\r\n\r\nTo do the inference, use the test.py file, you can use the following commands line to get the important arguments\r\n\r\nBASH2* \n"
      },
      "source": "https://raw.githubusercontent.com/w3user/SegDGAN/master/Readme.md",
      "technique": "supervised_classification"
    }
  ],
  "issue_tracker": [
    {
      "confidence": 1,
      "result": {
        "type": "Url",
        "value": "https://api.github.com/repos/w3user/SegDGAN/issues"
      },
      "technique": "GitHub_API"
    }
  ],
  "keywords": [
    {
      "confidence": 1,
      "result": {
        "type": "String",
        "value": ""
      },
      "technique": "GitHub_API"
    }
  ],
  "name": [
    {
      "confidence": 1,
      "result": {
        "type": "String",
        "value": "SegDGAN"
      },
      "technique": "GitHub_API"
    }
  ],
  "owner": [
    {
      "confidence": 1,
      "result": {
        "type": "User",
        "value": "w3user"
      },
      "technique": "GitHub_API"
    }
  ],
  "programming_languages": [
    {
      "confidence": 1,
      "result": {
        "name": "Python",
        "size": 50229,
        "type": "Programming_language",
        "value": "Python"
      },
      "technique": "GitHub_API"
    }
  ],
  "readme_url": [
    {
      "confidence": 1,
      "result": {
        "type": "Url",
        "value": "https://raw.githubusercontent.com/w3user/SegDGAN/master/Readme.md"
      },
      "technique": "file_exploration"
    }
  ],
  "somef_missing_categories": [
    "citation",
    "acknowledgement",
    "run",
    "download",
    "requirements",
    "contact",
    "description",
    "contributors",
    "documentation",
    "license",
    "usage",
    "faq",
    "support",
    "identifier",
    "has_build_file",
    "executable_example"
  ],
  "somef_provenance": {
    "date": "2024-10-06 13:42:17",
    "somef_schema_version": "1.0.0",
    "somef_version": "0.9.5"
  },
  "stargazers_count": [
    {
      "confidence": 1,
      "result": {
        "type": "Number",
        "value": 0
      },
      "technique": "GitHub_API"
    }
  ]
}