{
  "application_domain": [
    {
      "confidence": 22.79,
      "result": {
        "type": "String",
        "value": "Natural Language Processing"
      },
      "technique": "supervised_classification"
    }
  ],
  "citation": [
    {
      "confidence": 1,
      "result": {
        "original_header": "Citation",
        "parent_header": [
          "Sc2Mol: A Scaffold-based Two-step Molecule Generator with Variational Autoencoder and Transformer"
        ],
        "type": "Text_excerpt",
        "value": "Zhirui Liao, Lei Xie, Hiroshi Mamitsuka, Shanfeng Zhu, Sc2Mol: a scaffold-based two-step molecule generator with variational autoencoder and transformer, Bioinformatics, Volume 39, Issue 1, January 2023, btac814, https://doi.org/10.1093/bioinformatics/btac814\n"
      },
      "source": "https://raw.githubusercontent.com/zhiruiliao/Sc2Mol/main/README.md",
      "technique": "header_analysis"
    }
  ],
  "code_repository": [
    {
      "confidence": 1,
      "result": {
        "type": "Url",
        "value": "https://github.com/zhiruiliao/Sc2Mol"
      },
      "technique": "GitHub_API"
    }
  ],
  "contact": [
    {
      "confidence": 1,
      "result": {
        "original_header": "Contacts and bug reports",
        "parent_header": [
          "Sc2Mol: A Scaffold-based Two-step Molecule Generator with Variational Autoencoder and Transformer"
        ],
        "type": "Text_excerpt",
        "value": "Please feel free to send bug reports or questions to Zhirui Liao: zrliao19@fudan.edu.cn and Prof. Shanfeng Zhu: zhusf@fudan.edu.cn\n"
      },
      "source": "https://raw.githubusercontent.com/zhiruiliao/Sc2Mol/main/README.md",
      "technique": "header_analysis"
    }
  ],
  "contributing_guidelines": [
    {
      "confidence": 1,
      "result": {
        "original_header": "Evaluating (given scaffold)",
        "parent_header": [
          "Sc2Mol: A Scaffold-based Two-step Molecule Generator with Variational Autoencoder and Transformer"
        ],
        "type": "Text_excerpt",
        "value": "`python eval_from_scaffold.py --input INPUT_NPY --target TARGET_NPY --num_sample NUM_SAMPLE --output OUTPUT_FILE --ckpt CHECKPOINT_PATH`  \nMore arguments setting can be found and changed in code file `eval_from_scaffold.py`.  \n"
      },
      "source": "https://raw.githubusercontent.com/zhiruiliao/Sc2Mol/main/README.md",
      "technique": "header_analysis"
    }
  ],
  "date_created": [
    {
      "confidence": 1,
      "result": {
        "type": "Date",
        "value": "2022-05-15T14:18:34Z"
      },
      "technique": "GitHub_API"
    }
  ],
  "date_updated": [
    {
      "confidence": 1,
      "result": {
        "type": "Date",
        "value": "2024-09-05T07:20:56Z"
      },
      "technique": "GitHub_API"
    }
  ],
  "description": [
    {
      "confidence": 0.976547860396181,
      "result": {
        "original_header": "Recent update",
        "type": "Text_excerpt",
        "value": "2024-01-10: Fix a bug in `transformer.py`, which may cause error when `get_config` method is called.  \n2023-09-11:  Code is modified to support batch random generation. Much more faster!\n \n"
      },
      "source": "https://raw.githubusercontent.com/zhiruiliao/Sc2Mol/main/README.md",
      "technique": "supervised_classification"
    },
    {
      "confidence": 0.9786276441657109,
      "result": {
        "original_header": "Data",
        "type": "Text_excerpt",
        "value": "See `data` fold to get data and preprocess data.\n \n"
      },
      "source": "https://raw.githubusercontent.com/zhiruiliao/Sc2Mol/main/README.md",
      "technique": "supervised_classification"
    },
    {
      "confidence": 0.8617919754686256,
      "result": {
        "original_header": "Training",
        "type": "Text_excerpt",
        "value": "`python training.py --input_npy ./data/training_raw_chain --target_npy ./data/training_raw_target --npy_num 10`  \nMore arguments setting can be found and changed in code file `training.py`.  \n \n"
      },
      "source": "https://raw.githubusercontent.com/zhiruiliao/Sc2Mol/main/README.md",
      "technique": "supervised_classification"
    },
    {
      "confidence": 0.987581632128418,
      "result": {
        "original_header": "Declaration",
        "type": "Text_excerpt",
        "value": "It is free for non-commercial use. For commercial use, please contact with Zhirui Liao and Prof. Shanfeng Zhu (zhusf@fudan.edu.cn).\n \n"
      },
      "source": "https://raw.githubusercontent.com/zhiruiliao/Sc2Mol/main/README.md",
      "technique": "supervised_classification"
    }
  ],
  "download_url": [
    {
      "confidence": 1,
      "result": {
        "type": "Url",
        "value": "https://github.com/zhiruiliao/Sc2Mol/releases"
      },
      "technique": "GitHub_API"
    }
  ],
  "forks_count": [
    {
      "confidence": 1,
      "result": {
        "type": "Number",
        "value": 3
      },
      "technique": "GitHub_API"
    }
  ],
  "forks_url": [
    {
      "confidence": 1,
      "result": {
        "type": "Url",
        "value": "https://api.github.com/repos/zhiruiliao/Sc2Mol/forks"
      },
      "technique": "GitHub_API"
    }
  ],
  "full_name": [
    {
      "confidence": 1,
      "result": {
        "type": "String",
        "value": "zhiruiliao/Sc2Mol"
      },
      "technique": "GitHub_API"
    }
  ],
  "full_title": [
    {
      "confidence": 1,
      "result": {
        "type": "String",
        "value": "Sc2Mol: A Scaffold-based Two-step Molecule Generator with Variational Autoencoder and Transformer"
      },
      "source": "https://raw.githubusercontent.com/zhiruiliao/Sc2Mol/main/README.md",
      "technique": "regular_expression"
    }
  ],
  "installation": [
    {
      "confidence": 0.8094911857878189,
      "result": {
        "original_header": "Evaluating (random generation)",
        "type": "Text_excerpt",
        "value": "`python eval_random.py --num_sample NUM_SAMPLE --output OUTPUT --ckpt CHECKPOINT`  \nMore arguments setting can be found and changed in code file `eval_random.py`.  \n \n"
      },
      "source": "https://raw.githubusercontent.com/zhiruiliao/Sc2Mol/main/README.md",
      "technique": "supervised_classification"
    }
  ],
  "invocation": [
    {
      "confidence": 0.8896194242736732,
      "result": {
        "original_header": "Training",
        "type": "Text_excerpt",
        "value": "`python training.py --input_npy ./data/training_raw_chain --target_npy ./data/training_raw_target --npy_num 10`  \nMore arguments setting can be found and changed in code file `training.py`.  \n \n"
      },
      "source": "https://raw.githubusercontent.com/zhiruiliao/Sc2Mol/main/README.md",
      "technique": "supervised_classification"
    },
    {
      "confidence": 0.8919799579641465,
      "result": {
        "original_header": "Evaluating (random generation)",
        "type": "Text_excerpt",
        "value": "`python eval_random.py --num_sample NUM_SAMPLE --output OUTPUT --ckpt CHECKPOINT`  \nMore arguments setting can be found and changed in code file `eval_random.py`.  \n \n"
      },
      "source": "https://raw.githubusercontent.com/zhiruiliao/Sc2Mol/main/README.md",
      "technique": "supervised_classification"
    }
  ],
  "issue_tracker": [
    {
      "confidence": 1,
      "result": {
        "type": "Url",
        "value": "https://api.github.com/repos/zhiruiliao/Sc2Mol/issues"
      },
      "technique": "GitHub_API"
    }
  ],
  "keywords": [
    {
      "confidence": 1,
      "result": {
        "type": "String",
        "value": ""
      },
      "technique": "GitHub_API"
    }
  ],
  "name": [
    {
      "confidence": 1,
      "result": {
        "type": "String",
        "value": "Sc2Mol"
      },
      "technique": "GitHub_API"
    }
  ],
  "owner": [
    {
      "confidence": 1,
      "result": {
        "type": "User",
        "value": "zhiruiliao"
      },
      "technique": "GitHub_API"
    }
  ],
  "programming_languages": [
    {
      "confidence": 1,
      "result": {
        "name": "Python",
        "size": 70596,
        "type": "Programming_language",
        "value": "Python"
      },
      "technique": "GitHub_API"
    }
  ],
  "readme_url": [
    {
      "confidence": 1,
      "result": {
        "type": "Url",
        "value": "https://raw.githubusercontent.com/zhiruiliao/Sc2Mol/main/README.md"
      },
      "technique": "file_exploration"
    }
  ],
  "requirements": [
    {
      "confidence": 1,
      "result": {
        "original_header": "Requirements",
        "parent_header": [
          "Sc2Mol: A Scaffold-based Two-step Molecule Generator with Variational Autoencoder and Transformer"
        ],
        "type": "Text_excerpt",
        "value": "python 3.7  \ntensorflow-gpu >= 2.3.0  \nrdkit >= 2020.03.2.0  \npandas >= 1.0.3  \nnumpy >= 1.19.2 \n"
      },
      "source": "https://raw.githubusercontent.com/zhiruiliao/Sc2Mol/main/README.md",
      "technique": "header_analysis"
    }
  ],
  "somef_missing_categories": [
    "acknowledgement",
    "run",
    "download",
    "contributors",
    "documentation",
    "license",
    "usage",
    "faq",
    "identifier",
    "has_build_file",
    "executable_example"
  ],
  "somef_provenance": {
    "date": "2024-10-04 11:08:57",
    "somef_schema_version": "1.0.0",
    "somef_version": "0.9.5"
  },
  "stargazers_count": [
    {
      "confidence": 1,
      "result": {
        "type": "Number",
        "value": 13
      },
      "technique": "GitHub_API"
    }
  ],
  "support": [
    {
      "confidence": 1,
      "result": {
        "original_header": "Contacts and bug reports",
        "parent_header": [
          "Sc2Mol: A Scaffold-based Two-step Molecule Generator with Variational Autoencoder and Transformer"
        ],
        "type": "Text_excerpt",
        "value": "Please feel free to send bug reports or questions to Zhirui Liao: zrliao19@fudan.edu.cn and Prof. Shanfeng Zhu: zhusf@fudan.edu.cn\n"
      },
      "source": "https://raw.githubusercontent.com/zhiruiliao/Sc2Mol/main/README.md",
      "technique": "header_analysis"
    }
  ],
  "type": [
    {
      "confidence": 0.82,
      "result": {
        "type": "String",
        "value": "commandline-application"
      },
      "technique": "software_type_heuristics"
    }
  ]
}